ymmsl_dot/__init__.py
ymmsl_dot/main.py
ymmsl_dot/model_to_dot.py
ymmsl_dot-0.1.2.dist-info/LICENSE
ymmsl_dot-0.1.2.dist-info/METADATA
ymmsl_dot-0.1.2.dist-info/WHEEL
ymmsl_dot-0.1.2.dist-info/entry_points.txt
ymmsl_dot-0.1.2.dist-info/top_level.txt
ymmsl_dot-0.1.2.dist-info/RECORD
