Metadata-Version: 2.1
Name: ymmsl-dot
Version: 0.1.2
Summary: Visualise yMMSL models with graphviz.
Home-page: https://github.com/DaanVanVugt/ymmsl-dot
Author: Daan van Vugt
Author-email: dvanvugt@ignitioncomputing.com
License: Apache 2.0
Project-URL: webpage, https://github.com/DaanVanVugt/ymmsl-dot
Project-URL: Documentation, https://ymmsl-dot.readthedocs.io/en/latest/
Project-URL: Issue Tracker, https://github.com/DaanVanVugt/ymmsl-dot/issues
Project-URL: Discussion Forum, https://github.com/DaanVanVugt/ymmsl-dot/discussions
Keywords: ymmsl,simulation,graphviz,dot,muscle3,yMMSL,multiscale
Classifier: Development Status :: 4 - Beta
Classifier: License :: OSI Approved :: Apache Software License
Classifier: Intended Audience :: Science/Research
Classifier: Natural Language :: English
Classifier: Operating System :: POSIX
Classifier: Operating System :: MacOS
Classifier: Operating System :: Microsoft
Classifier: Programming Language :: Python :: 3.7
Classifier: Programming Language :: Python :: 3.8
Classifier: Programming Language :: Python :: 3.9
Classifier: Programming Language :: Python :: 3.10
Classifier: Topic :: Scientific/Engineering :: Bio-Informatics
Requires-Python: >=3.7, <4
License-File: LICENSE
Requires-Dist: pydot (>=1)
Requires-Dist: ymmsl
Requires-Dist: click
